{"app":["/app.42cac0110bedc0ca2c64.js"],"component---src-pages-404-js":["/component---src-pages-404-js.d33fb2013e1c95c937b9.css","/component---src-pages-404-js.1885447c535b5feac796.js"],"component---src-pages-about-index-js":["/component---src-pages-about-index-js.5b1769d1d7e9d6c585b7.js"],"component---src-pages-home-index-js":["/component---src-pages-home-index-js.5ce899918d6b7800d4ca.css","/component---src-pages-home-index-js.2c5e6ccf01d646294274.js"],"component---src-pages-index-js":["/component---src-pages-index-js.4a1c7a3afb40edc980db.css","/component---src-pages-index-js.4fde54eac0b96cb24012.js"],"pages-manifest":["/pages-manifest.098aa9a2aed286aea204.js"]}